Speed_test_OOkla
