Metadata-Version: 1.1
Name: Speed-test-OOkla
Version: 0.0.1
Summary: Okla Speed test automation
Home-page: UNKNOWN
Author: Amrit Lal Gaur
Author-email: amrit.gaur549@gmail.com
License: MIT
Keywords: speedtestautomation
Platform: UNKNOWN
Classifier: Development Status :: 5 - Production/Stable
Classifier: Intended Audience :: Education
Classifier: Operating System :: Microsoft :: Windows :: Windows 10
Classifier: License :: OSI Approved :: MIT License
Classifier: Programming Language :: Python :: 3
